jbussdieker/bar.py
jbussdieker3-0.1.0.dist-info/licenses/LICENSE
jbussdieker3-0.1.0.dist-info/METADATA
jbussdieker3-0.1.0.dist-info/WHEEL
jbussdieker3-0.1.0.dist-info/top_level.txt
jbussdieker3-0.1.0.dist-info/RECORD
