Metadata-Version: 2.4
Name: jbussdieker3
Version: 0.1.0
Summary: Generated by jbussdieker.
Author-email: "Joshua B. Bussdieker" <jbussdieker@gmail.com>
Maintainer-email: "Joshua B. Bussdieker" <jbussdieker@gmail.com>
License-Expression: MIT
Project-URL: Homepage, https://github.com/jbussdieker/python-jbussdieker3
Project-URL: Documentation, https://github.com/jbussdieker/python-jbussdieker3/blob/master/README.md
Project-URL: Repository, https://github.com/jbussdieker/python-jbussdieker3
Project-URL: Issues, https://github.com/jbussdieker/python-jbussdieker3/issues
Project-URL: Changelog, https://github.com/jbussdieker/python-jbussdieker3/blob/master/CHANGELOG.md
Classifier: Topic :: Software Development :: Build Tools
Classifier: Development Status :: 3 - Alpha
Classifier: Programming Language :: Python :: 3
Classifier: Programming Language :: Python :: 3.9
Classifier: Programming Language :: Python :: 3.10
Classifier: Programming Language :: Python :: 3.11
Classifier: Programming Language :: Python :: 3.12
Classifier: Programming Language :: Python :: 3.13
Classifier: Operating System :: OS Independent
Classifier: Environment :: Console
Classifier: Intended Audience :: Developers
Classifier: Natural Language :: English
Classifier: Typing :: Typed
Requires-Python: >=3.9
License-File: LICENSE
Dynamic: license-file
